deflatabledict/__init__.py
deflatabledict/deflatable.py
deflatable_dict-0.3.0.dist-info/LICENSE
deflatable_dict-0.3.0.dist-info/METADATA
deflatable_dict-0.3.0.dist-info/WHEEL
deflatable_dict-0.3.0.dist-info/top_level.txt
deflatable_dict-0.3.0.dist-info/RECORD
