Metadata-Version: 2.1
Name: deflatable-dict
Version: 0.3.0
Summary: A dictionary that can be flattened and re-inflated
Home-page: https://github.com/JJ11teen/deflatable-dict
Author: Lucas Sargent
Author-email: lucas.sargent@eliiza.com.au
License: UNKNOWN
Project-URL: Bug Tracker, https://github.com/JJ11teen/deflatable-dict/issues
Keywords: dict flatten nested yaml yaml
Platform: UNKNOWN
Classifier: Programming Language :: Python :: 3
Classifier: License :: OSI Approved :: MIT License
Classifier: Operating System :: OS Independent
Requires-Python: >=3.6
License-File: LICENSE
Provides-Extra: tests
Requires-Dist: pytest (==6.2.4) ; extra == 'tests'
